{"directed":true,"nodes":[{"viewpoint":null,"visibility":"PUBLIC_LITERAL","qualifiedName":"model","name":"model","id":0,"URI":null,"eClass":"Model"},{"visibility":"PUBLIC_LITERAL","id":1,"eClass":"PackageImport"},{"visibility":"PUBLIC_LITERAL","qualifiedName":"model::Player","name":"Player","id":2,"isActive":false,"isLeaf":false,"isAbstract":false,"isFinalSpecialization":false,"eClass":"Class"},{"visibility":"PUBLIC_LITERAL","qualifiedName":"model::Game","name":"Game","id":3,"isActive":false,"isLeaf":false,"isAbstract":false,"isFinalSpecialization":false,"eClass":"Class"},{"visibility":"PUBLIC_LITERAL","qualifiedName":"model::Grid","name":"Grid","id":4,"isActive":false,"isLeaf":false,"isAbstract":false,"isFinalSpecialization":false,"eClass":"Class"},{"visibility":"PUBLIC_LITERAL","qualifiedName":"model::Square","name":"Square","id":5,"isActive":false,"isLeaf":false,"isAbstract":false,"isFinalSpecialization":false,"eClass":"Class"},{"visibility":"PUBLIC_LITERAL","qualifiedName":"model::Piece","name":"Piece","id":6,"isActive":false,"isLeaf":false,"isAbstract":false,"isFinalSpecialization":false,"eClass":"Class"},{"isDerived":false,"visibility":"PUBLIC_LITERAL","qualifiedName":"model::Player_Game","name":"Player_Game","id":7,"isLeaf":false,"isAbstract":false,"isFinalSpecialization":false,"eClass":"Association"},{"isDerived":false,"visibility":"PUBLIC_LITERAL","qualifiedName":"model::Game_Grid","name":"Game_Grid","id":8,"isLeaf":false,"isAbstract":false,"isFinalSpecialization":false,"eClass":"Association"},{"isDerived":false,"visibility":"PUBLIC_LITERAL","qualifiedName":"model::Grid_Square","name":"Grid_Square","id":9,"isLeaf":false,"isAbstract":false,"isFinalSpecialization":false,"eClass":"Association"},{"isDerived":false,"visibility":"PUBLIC_LITERAL","qualifiedName":"model::Square_Piece","name":"Square_Piece","id":10,"isLeaf":false,"isAbstract":false,"isFinalSpecialization":false,"eClass":"Association"},{"visibility":"PUBLIC_LITERAL","qualifiedName":"model::Checker","name":"Checker","id":11,"isActive":false,"isLeaf":false,"isAbstract":false,"isFinalSpecialization":false,"eClass":"Class"},{"visibility":"PUBLIC_LITERAL","qualifiedName":"model::King","name":"King","id":12,"isActive":false,"isLeaf":false,"isAbstract":false,"isFinalSpecialization":false,"eClass":"Class"},{"isDerived":false,"visibility":"PUBLIC_LITERAL","qualifiedName":"model::Player_Piece","name":"Player_Piece","id":13,"isLeaf":false,"isAbstract":false,"isFinalSpecialization":false,"eClass":"Association"},{"visibility":"PUBLIC_LITERAL","qualifiedName":"model::Spectator","name":"Spectator","id":14,"isActive":false,"isLeaf":false,"isAbstract":false,"isFinalSpecialization":false,"eClass":"Class"},{"isDerived":false,"visibility":"PUBLIC_LITERAL","qualifiedName":"model::Spectator_Game","name":"Spectator_Game","id":15,"isLeaf":false,"isAbstract":false,"isFinalSpecialization":false,"eClass":"Association"},{"isStatic":false,"isDerived":false,"visibility":"PUBLIC_LITERAL","qualifiedName":"model::Player_Game::game","lower":0,"upper":-1,"isUnique":true,"aggregation":"NONE_LITERAL","isLeaf":false,"eClass":"Property","default":null,"isReadOnly":false,"isComposite":false,"isID":false,"isDerivedUnion":false,"name":"game","id":16,"isOrdered":false},{"isStatic":false,"isDerived":false,"visibility":"PUBLIC_LITERAL","qualifiedName":"model::Player_Game::player","lower":0,"upper":2,"isUnique":true,"aggregation":"NONE_LITERAL","isLeaf":false,"eClass":"Property","default":null,"isReadOnly":false,"isComposite":false,"isID":false,"isDerivedUnion":false,"name":"player","id":17,"isOrdered":false},{"visibility":"PUBLIC_LITERAL","qualifiedName":null,"name":null,"id":18,"value":0,"eClass":"LiteralInteger"},{"visibility":"PUBLIC_LITERAL","qualifiedName":null,"name":null,"id":19,"value":-1,"eClass":"LiteralUnlimitedNatural"},{"visibility":"PUBLIC_LITERAL","qualifiedName":null,"name":null,"id":20,"value":0,"eClass":"LiteralInteger"},{"visibility":"PUBLIC_LITERAL","qualifiedName":null,"name":null,"id":21,"value":2,"eClass":"LiteralUnlimitedNatural"},{"isStatic":false,"isDerived":false,"visibility":"PUBLIC_LITERAL","qualifiedName":"model::Game_Grid::grid","lower":1,"upper":1,"isUnique":true,"aggregation":"NONE_LITERAL","isLeaf":false,"eClass":"Property","default":null,"isReadOnly":false,"isComposite":false,"isID":false,"isDerivedUnion":false,"name":"grid","id":22,"isOrdered":false},{"isStatic":false,"isDerived":false,"visibility":"PUBLIC_LITERAL","qualifiedName":"model::Game_Grid::game","lower":1,"upper":1,"isUnique":true,"aggregation":"NONE_LITERAL","isLeaf":false,"eClass":"Property","default":null,"isReadOnly":false,"isComposite":false,"isID":false,"isDerivedUnion":false,"name":"game","id":23,"isOrdered":false},{"visibility":"PUBLIC_LITERAL","qualifiedName":null,"name":null,"id":24,"value":1,"eClass":"LiteralInteger"},{"visibility":"PUBLIC_LITERAL","qualifiedName":null,"name":null,"id":25,"value":1,"eClass":"LiteralUnlimitedNatural"},{"visibility":"PUBLIC_LITERAL","qualifiedName":null,"name":null,"id":26,"value":1,"eClass":"LiteralInteger"},{"visibility":"PUBLIC_LITERAL","qualifiedName":null,"name":null,"id":27,"value":1,"eClass":"LiteralUnlimitedNatural"},{"isStatic":false,"isDerived":false,"visibility":"PUBLIC_LITERAL","qualifiedName":"model::Grid_Square::square","lower":0,"upper":-1,"isUnique":true,"aggregation":"NONE_LITERAL","isLeaf":false,"eClass":"Property","default":null,"isReadOnly":false,"isComposite":false,"isID":false,"isDerivedUnion":false,"name":"square","id":28,"isOrdered":false},{"isStatic":false,"isDerived":false,"visibility":"PUBLIC_LITERAL","qualifiedName":"model::Grid_Square::grid","lower":1,"upper":1,"isUnique":true,"aggregation":"NONE_LITERAL","isLeaf":false,"eClass":"Property","default":null,"isReadOnly":false,"isComposite":false,"isID":false,"isDerivedUnion":false,"name":"grid","id":29,"isOrdered":false},{"visibility":"PUBLIC_LITERAL","qualifiedName":null,"name":null,"id":30,"value":0,"eClass":"LiteralInteger"},{"visibility":"PUBLIC_LITERAL","qualifiedName":null,"name":null,"id":31,"value":-1,"eClass":"LiteralUnlimitedNatural"},{"visibility":"PUBLIC_LITERAL","qualifiedName":null,"name":null,"id":32,"value":1,"eClass":"LiteralInteger"},{"visibility":"PUBLIC_LITERAL","qualifiedName":null,"name":null,"id":33,"value":1,"eClass":"LiteralUnlimitedNatural"},{"isStatic":false,"isDerived":false,"visibility":"PUBLIC_LITERAL","qualifiedName":"model::Square_Piece::piece","lower":1,"upper":1,"isUnique":true,"aggregation":"NONE_LITERAL","isLeaf":false,"eClass":"Property","default":null,"isReadOnly":false,"isComposite":false,"isID":false,"isDerivedUnion":false,"name":"piece","id":34,"isOrdered":false},{"isStatic":false,"isDerived":false,"visibility":"PUBLIC_LITERAL","qualifiedName":"model::Square_Piece::square","lower":1,"upper":1,"isUnique":true,"aggregation":"NONE_LITERAL","isLeaf":false,"eClass":"Property","default":null,"isReadOnly":false,"isComposite":false,"isID":false,"isDerivedUnion":false,"name":"square","id":35,"isOrdered":false},{"visibility":"PUBLIC_LITERAL","qualifiedName":null,"name":null,"id":36,"value":1,"eClass":"LiteralInteger"},{"visibility":"PUBLIC_LITERAL","qualifiedName":null,"name":null,"id":37,"value":1,"eClass":"LiteralUnlimitedNatural"},{"visibility":"PUBLIC_LITERAL","qualifiedName":null,"name":null,"id":38,"value":1,"eClass":"LiteralInteger"},{"visibility":"PUBLIC_LITERAL","qualifiedName":null,"name":null,"id":39,"value":1,"eClass":"LiteralUnlimitedNatural"},{"isStatic":false,"isDerived":false,"visibility":"PUBLIC_LITERAL","qualifiedName":"model::Player_Piece::piece","lower":0,"upper":1,"isUnique":true,"aggregation":"NONE_LITERAL","isLeaf":false,"eClass":"Property","default":null,"isReadOnly"t":17},{"source":7,"target":16},{"source":7,"target":17},{"source":16,"target":3},{"source":16,"target":18},{"source":16,"target":19},{"source":16,"target":7},{"source":16,"target":7},{"source":17,"target":2},{"source":17,"target":20},{"source":17,"target":21},{"source":17,"target":7},{"source":17,"target":7},{"source":8,"target":22},{"source":8,"target":23},{"source":8,"target":22},{"source":8,"target":23},{"source":8,"target":22},{"source":8,"target":23},{"source":22,"target":4},{"source":22,"target":24},{"source":22,"target":25},{"source":22,"target":8},{"source":22,"target":8},{"source":23,"target":3},{"source":23,"target":26},{"source":23,"target":27},{"source":23,"target":8},{"source":23,"target":8},{"source":9,"target":28},{"source":9,"target":29},{"source":9,"target":28},{"source":9,"target":29},{"source":9,"target":28},{"source":9,"target":29},{"source":28,"target":5},{"source":28,"target":30},{"source":28,"target":31},{"source":28,"target":9},{"source":28,"target":9},{"source":29,"target":4},{"source":29,"target":32},{"source":29,"target":33},{"source":29,"target":9},{"source":29,"target":9},{"source":10,"target":34},{"source":10,"target":35},{"source":10,"target":34},{"source":10,"target":35},{"source":10,"target":34},{"source":10,"target":35},{"source":34,"target":6},{"source":34,"target":36},{"source":34,"target":37},{"source":34,"target":10},{"source":34,"target":10},{"source":35,"target":5},{"source":35,"target":38},{"source":35,"target":39},{"source":35,"target":10},{"source":35,"target":10},{"source":13,"target":40},{"source":13,"target":41},{"source":13,"target":40},{"source":13,"target":41},{"source":13,"target":40},{"source":13,"target":41},{"source":40,"target":6},{"source":40,"target":42},{"source":40,"target":43},{"source":40,"target":13},{"source":40,"target":13},{"source":41,"target":2},{"source":41,"target":44},{"source":41,"target":45},{"source":41,"target":13},{"source":41,"target":13},{"source":15,"target":46},{"source":15,"target":47},{"source":15,"target":46},{"source":15,"target":47},{"source":15,"target":46},{"source":15,"target":47},{"source":46,"target":3},{"source":46,"target":48},{"source":46,"target":49},{"source":46,"target":15},{"source":46,"target":15},{"source":47,"target":14},{"source":47,"target":50},{"source":47,"target":51},{"source":47,"target":15},{"source":47,"target":15}],"multigraph":true}