{"directed":true,"nodes":[{"viewpoint":null,"visibility":"PUBLIC_LITERAL","qualifiedName":"model","name":"model","id":0,"URI":null,"eClass":"Model"},{"visibility":"PUBLIC_LITERAL","id":1,"eClass":"PackageImport"},{"isSingle7,"body":[],"isLeaf":false,"eClass":"OpaqueAction"},{"visibility":"PUBLIC_LITERAL","qualifiedName":"Request data ","isLocallyReentrant":false,"name":"Request data ","language":[],"id":18,"body":[],"isLeaf":false,"eClass":"OpaqueAction"},{"visibility":"PUBLIC_LITERAL","qualifiedName":"Memproses request data base","isLocallyReentrant":false,"name":"Memproses request data base","language":[],"id":19,"body":[],"isLeaf":false,"eClass":"OpaqueAction"},{"visibility":"PUBLIC_LITERAL","qualifiedName":"Menampilkan hasil ","isLocallyReentrant":false,"name":"Menampilkan hasil ","language":[],"id":20,"body":[],"isLeaf":false,"eClass":"OpaqueAction"},{"visibility":"PUBLIC_LITERAL","qualifiedName":"JoinNode","name":"JoinNode","id":21,"isLeaf":false,"isCombineDuplicate":true,"eClass":"JoinNode"},{"visibility":"PUBLIC_LITERAL","qualifiedName":"JoinNode2","name":"JoinNode2","id":22,"isLeaf":false,"isCombineDuplicate":true,"eClass":"JoinNode"},{"visibility":"PUBLIC_LITERAL","qualifiedName":"JoinNode3","name":"JoinNode3","id":23,"isLeaf":false,"isCombineDuplicate":true,"eClass":"JoinNode"},{"visibility":"PUBLIC_LITERAL","qualifiedName":"JoinNode32","name":"JoinNode32","id":24,"isLeaf":false,"isCombineDuplicate":true,"eClass":"JoinNode"},{"visibility":"PUBLIC_LITERAL","qualifiedName":"DecisionNode","name":"DecisionNode","id":25,"isLeaf":false,"eClass":"DecisionNode"},{"visibility":"PUBLIC_LITERAL","qualifiedName":"Tampil Error","isLocallyReentrant":false,"name":"Tampil Error","language":[],"id":26,"body":[],"isLeaf":false,"eClass":"OpaqueAction"},{"visibility":"PUBLIC_LITERAL","qualifiedName":null,"name":null,"id":27,"value":"start","eClass":"LiteralString"},{"visibility":"PUBLIC_LITERAL","qualifiedName":null,"name":null,"id":28,"value":"true","eClass":"LiteralString"},{"visibility":"PUBLIC_LITERAL","qualifiedName":null,"name":null,"id":29,"value":"true","eClass":"LiteralString"},{"visibility":"PUBLIC_LITERAL","qualifiedName":null,"name":null,"id":30,"value":"Finish","eClass":"LiteralString"},{"visibility":"PUBLIC_LITERAL","qualifiedName":null,"name":null,"id":31,"value":"true","eClass":"LiteralString"},{"visibility":"PUBLIC_LITERAL","qualifiedName":null,"name":null,"id":32,"value":" True","eClass":"LiteralString"},{"visibility":"PUBLIC_LITERAL","qualifiedName":null,"name":null,"id":33,"value":"False","eClass":"LiteralString"},{"visibility":"PUBLIC_LITERAL","qualifiedName":null,"name":null,"id":34,"value":"true","eClass":"LiteralString"},{"visibility":"PUBLIC_LITERAL","qualifiedName":"ControlFlow","name":"ControlFlow","id":35,"isLeaf":false,"eClass":"ControlFlow"},{"visibility":"PUBLIC_LITERAL","qualifiedName":"ControlFlow2","name":"ControlFlow2","id":36,"isLeaf":false,"eClass":"ControlFlow"},{"visibility":"PUBLIC_LITERAL","qualifiedName":"ControlFlow3","name":"ControlFlow3","id":37,"isLeaf":false,"eClass":"ControlFlow"},{"visibility":"PUBLIC_LITERAL","qualifiedName":"ControlFlow4","name":"ControlFlow4","id":38,"isLeaf":false,"eClass":"ControlFlow"},{"visibility":"PUBLIC_LITERAL","qualifiedName":"ControlFlow5","name":"ControlFlow5","id":39,"isLeaf":false,"eClass":"ControlFlow"},{"visibility":"PUBLIC_LITERAL","qualifiedName":"ActivityFinalNode","name":"ActivityFinalNode","id":40,"isLeaf":false,"eClass":"ActivityFinalNode"},{"visibility":"PUBLIC_LITERAL","qualifiedName":"InitialNode","name":"InitialNode","id":41,"isLeaf":false,"eClass":"InitialNode"},{"visibility":"PUBLIC_LITERAL","qualifiedName":"Melakukan permohonan","isLocallyReentrant":false,"name":"Melakukan permohonan","language":[],"id":42,"body":[],"isLeaf":false,"eClass":"OpaqueAction"},{"visibility":"PUBLIC_LITERAL","qualifiedName":"Request permohonan","isLocallyReentrant":false,"name":"Request permohonan","language":[],"id":43,"body":[],"isLeaf":false,"eClass":"OpaqueAction"},{"visibility":"PUBLIC_LITERAL","qualifiedName":"Menampilkan form permohonan","isLocallyReentrant":false,"name":"Menampilkan form permohonan","language":[],"id":44,"body":[],"isLeaf":false,"eClass":"OpaqueAction"},{"visibility":"PUBLIC_LITERAL","qualifiedName":"Mengisi permohonan","isLocallyReentrant":false,"name":"Mengisi permohonan","language":[],"id":45,"body":[],"isLeaf":false,"eClass":"OpaqueAction"},{"visibility":"PUBLIC_LITERAL","qualifiedName":"ForkNode","name":"ForkNode","id":46,"isLeaf":false,"eClass":"ForkNode"},{"visibility":"PUBLIC_LITERAL","qualifiedName":"ForkNode2","name":"ForkNode2","id":47,"isLeaf":false,"eClass":"ForkNode"},{"visibility":"PUBLIC_LITERAL","qualifiedName":"ForkNode3","name":"ForkNode3","id":48,"isLeaf":false,"eClass":"ForkNode"},{"visibility":"PUBLIC_LITERAL","qualifiedName":null,"name":null,"id":49,"value":"Start","eClass":"LiteralString"},{"visibility":"PUBLIC_LITERAL","qualifiedName":null,"name":null,"id":50,"value":"true","eClass":"LiteralString"},{"visibility":"PUBLIC_LITERAL","qualifiedName":null,"name":null,"id":51,"value":"true","eClass":"LiteralString"},{"visibility":"PUBLIC_LITERAL","qualifiedName":null,"name":null,"id":52,"value":"true","eClass":"LiteralString"},{"visibility":"PUBLIC_LITERAL","qualifiedName":null,"name":null,"id":53,"value":"Finish","eClass":"LiteralString"}],"links":[{"source":0,"target":1},{"source":0,"target":2},{"source":0,"target":3},{"source":1,"target":0},{"source":2,"target":4},{"source":2,"target":5},{"source":2,"target":6},{"source":2,"target":7},{"source":2,"target":8},{"source":2,"target":9},{"source":2,"target":10},{"source":2,"target":11},{"source":2,"target":12},{"source":2,"target":13},{"source":2,"target":14},{"source":2,"target":15},{"source":2,"target":16},{"source":2,"target":17},{"source":2,"target":18},{"source":2,"target":19},{"source":2,"target":20},{"source":2,"target":21},{"source":2,"target":22},{"source":2,"target":23},{"source":2,"target":24},{"source":2,"target":25},{"source":2,"target":26},{"source":7,"target":2},{"source":7,"target":27},{"source":7,"target":17},{"source":7,"target":16},{"source":8,"target":2},{"source":8,"target":28},{"source":8,"target":18},{"source":8,"target":17},{"source":9,"target":2},{"source":9,"target":29},{"source":9,"target":19},{"source":9,"target":18},{"source":10,"target":2},{"source":10,"target":30},{"source":10,"target":15},{"source":10,"target":20},{"source":11,"target":2},{"source":11,"target":31},{"source":11,"target":25},{"source":11,"target":19},{"source":12,"target":2},{"source":12,"target":32},{"source":12,"target":20},{"source":12,"target":25},{"source":13,"target":2},{"source":13,"target":33},{"source":13,"target":26},{"source":13,"target":25},{"source":14,"target":2},{"source":14,"target":34},{"source":14,"target":17},{"source":14,"target":26},{"source":15,"target":10},{"source":16,"target":7},{"source":17,"target":7},{"source":17,"target":14},{"source":17,"target":8},{"source":18,"target":8},{"source":18,"target":9},{"source":19,"target":9},{"source":19,"target":11},{"source":20,"target":12},{"source":20,"target":10},{"source":25,"target":11},{"source":25,"target":12},{"source":25,"target":13},{"source":26,"target":13},{"source":26,"target":14},{"source":3,"target":35},{"source":3,"target":36},{"source":3,"target":37},{"source":3,"target":38},{"source":3,"target":39},{"source":3,"target":40},{"source":3,"target":41},{"source":3,"target":42},{"source":3,"target":43},{"source":3,"target":44},{"source":3,"target":45},{"source":3,"target":46},{"source":3,"target":47},{"source":3,"target":48},{"source":35,"target":3},{"source":35,"target":49},{"source":35,"target":42},{"source":35,"target":41},{"source":36,"target":3},{"source":36,"target":50},{"source":36,"target":43},{"source":36,"target":42},{"source":37,"target":3},{"source":37,"target":51},{"source":37,"target":44},{"source":37,"target":43},{"source":38,"target":3},{"source":38,"target":52},{"source":38,"target":45},{"source":38,"target":44},{"source":39,"target":3},{"source":39,"target":53},{"source":39,"target":40},{"source":39,"target":45},{"source":40,"target":39},{"source":41,"target":35},{"source":42,"target":35},{"source":42,"target":36},{"source":43,"target":36},{"source":43,"target":37},{"source":44,"target":37},{"source":44,"target":38},{"source":45,"target":38},{"source":45,"target":39}],"multigraph":true}