{"directed":true,"nodes":[{"viewpoint":null,"visibility":"PUBLIC_LITERAL","qualifiedName":"model","name":"model","id":0,"URI":null,"eClass":"Model"},{"visibility":"PUBLIC_LITERAL","id":1,"eClass":"PackageImport"},{"visibility":"PUBLIC_LITERAL","qualifiedName":"model::Y","name":"Y","id":2,"isActive":false,"isLeaf":false,"isAbstract":false,"isFinalSpecialization":false,"eClass":"Class"},{"visibility":"PUBLIC_LITERAL","qualifiedName":"model::R","name":"R","id":3,"isActive":false,"isLeaf":false,"isAbstract":false,"isFinalSpecialization":false,"eClass":"Class"},{"visibility":"PUBLIC_LITERAL","qualifiedName":"model::A","name":"A","id":4,"isActive":false,"isLeaf":false,"isAbstract":true,"isFinalSpecialization":false,"eClass":"Class"},{"visibility":"PUBLIC_LITERAL","qualifiedName":"model::B","name":"B","id":5,"isActive":false,"isLeaf":false,"isAbstract":false,"isFinalSpecialization":false,"eClass":"Class"},{"visibility":"PUBLIC_LITERAL","qualifiedName":"model::C","name":"C","id":6,"isActive":false,"isLeaf":false,"isAbstract":true,"isFinalSpecialization":false,"eClass":"Class"},{"visibility":"PUBLIC_LITERAL","qualifiedName":"model::C2","name":"C2","id":7,"isActive":false,"isLeaf":false,"isAbstract":false,"isFinalSpecialization":false,"eClass":"Class"},{"visibility":"PUBLIC_LITERAL","qualifiedName":"model::C3","name":"C3","id":8,"isActive":false,"isLeaf":false,"isAbstract":false,"isFinalSpecialization":false,"eClass":"Class"},{"visibility":"PUBLIC_LITERAL","qualifiedName":"model::Z","name":"Z","id":9,"isActive":false,"isLeaf":false,"isAbstract":false,"isFinalSpecialization":false,"eClass":"Class"},{"isDerived":false,"visibility":"PUBLIC_LITERAL","qualifiedName":"model::A_B","name":"A_B","id":10,"isLeaf":false,"isAbstract":false,"isFinalSpecialization":false,"eClass":"Association"},{"isDerived":false,"visibility":"PUBLIC_LITERAL","qualifiedName":"model::R_A","name":"R_A","id":11,"isLeaf":false,"isAbstract":false,"isFinalSpecialization":false,"eClass":"Association"},{"isDerived":false,"visibility":"PUBLIC_LITERAL","qualifiedName":"model::B_C","name":"B_C","id":12,"isLeaf":false,"isAbstract":false,"isFinalSpecialization":false,"eClass":"Association"},{"isStatic":false,"isDerived":false,"visibility":"PUBLIC_LITERAL","qualifiedName":"model::Y::attY","lower":1,"upper":1,"isUnique":true,"aggregation":"NONE_LITERAL","isLeaf":false,"eClass":"Property","default":null,"isReadOnly":false,"isComposite":false,"isID":false,"isDerivedUnion":false,"name":"attY","id":13,"isOrdered":false},{"isSubstitutable":true,"id":14,"eClass":"Generalization"},{"isStatic":false,"isDerived":false,"visibility":"PUBLIC_LITERAL","qualifiedName":"model::A::attA","lower":1,"upper":1,"isUnique":true,"aggregation":"NONE_LITERAL","isLeaf":false,"eClass":"Property","default":null,"isReadOnly":false,"isComposite":false,"isID":false,"isDerivedUnion":false,"name":"attA","id":15,"isOrdered":false},{"isStatic":false,"isDerived":false,"visibility":"PUBLIC_LITERAL","qualifiedName":"model::B::attB","lower":1,"upper":1,"isUnique":true,"aggregation":"NONE_LITERAL","isLeaf":false,"eClass":"Property","default":null,"isReadOnly":false,"isComposite":false,"isID":false,"isDerivedUnion":false,"name":"attB","id":16,"isOrdered":false},{"isStatic":false,"isDerived":false,"visibility":"PUBLIC_LITERAL","qualifiedName":"model::C::attC1","lower":1,"upper":1,"isUnique":true,"aggregation":"Nlower":0,"upper":-1,"isUnique":true,"aggregation":"SHARED_LITERAL","isLeaf":false,"eClass":"Property","default":null,"isReadOnly":false,"isComposite":false,"isID":false,"isDerivedUnion":false,"name":"aR","id":28,"isOrdered":false},{"isStatic":false,"isDerived":false,"visibility":"PUBLIC_LITERAL","qualifiedName":"model::R_A::r","lower":0,"upper":1,"isUnique":true,"aggregation":"NONE_LITERAL","isLeaf":false,"eClass":"Property","default":null,"isReadOnly":false,"isComposite":false,"isID":false,"isDerivedUnion":false,"name":"r","id":29,"isOrdered":false},{"visibility":"PUBLIC_LITERAL","qualifiedName":null,"name":null,"id":30,"value":0,"eClass":"LiteralInteger"},{"visibility":"PUBLIC_LITERAL","qualifiedName":null,"name":null,"id":31,"value":-1,"eClass":"LiteralUnlimitedNatural"},{"visibility":"PUBLIC_LITERAL","qualifiedName":null,"name":null,"id":32,"value":0,"eClass":"LiteralInteger"},{"visibility":"PUBLIC_LITERAL","qualifiedName":null,"name":null,"id":33,"value":1,"eClass":"LiteralUnlimitedNatural"},{"isStatic":false,"isDerived":false,"visibility":"PUBLIC_LITERAL","qualifiedName":"model::B_C::c","lower":0,"upper":-1,"isUnique":true,"aggregation":"NONE_LITERAL","isLeaf":false,"eClass":"Property","default":null,"isReadOnly":false,"isComposite":false,"isID":false,"isDerivedUnion":false,"name":"c","id":34,"isOrdered":false},{"isStatic":false,"isDerived":false,"visibility":"PUBLIC_LITERAL","qualifiedName":"model::B_C::b","lower":0,"upper":1,"isUnique":true,"aggregation":"NONE_LITERAL","isLeaf":false,"eClass":"Property","default":null,"isReadOnly":false,"isComposite":false,"isID":false,"isDerivedUnion":false,"name":"b","id":35,"isOrdered":false},{"visibility":"PUBLIC_LITERAL","qualifiedName":null,"name":null,"id":36,"value":0,"eClass":"LiteralInteger"},{"visibility":"PUBLIC_LITERAL","qualifiedName":null,"name":null,"id":37,"value":-1,"eClass":"LiteralUnlimitedNatural"},{"visibility":"PUBLIC_LITERAL","qualifiedName":null,"name":null,"id":38,"value":0,"eClass":"LiteralInteger"},{"visibility":"PUBLIC_LITERAL","qualifiedName":null,"name":null,"id":39,"value":1,"eClass":"LiteralUnlimitedNatural"}],"links":[{"source":0,"target":1},{"source":0,"target":2},{"source":0,"target":3},{"source":0,"target":4},{"source":0,"target":5},{"source":0,"target":6},{"source":0,"target":7},{"source":0,"target":8},{"source":0,"target":9},{"source":0,"target":10},{"source":0,"target":11},{"source":0,"target":12},{"source":1,"target":0},{"source":2,"target":13},{"source":13,"target":2},{"source":4,"target":14},{"source":4,"target":15},{"source":14,"target":2},{"source":14,"target":4},{"source":15,"target":4},{"source":5,"target":16},{"source":16,"target":5},{"source":6,"target":17},{"source":6,"target":18},{"source":17,"target":6},{"source":18,"target":6},{"source":7,"target":19},{"source":19,"target":6},{"source":19,"target":7},{"source":8,"target":20},{"source":20,"target":6},{"source":20,"target":8},{"source":9,"target":21},{"source":21,"target":4},{"source":21,"target":9},{"source":10,"target":22},{"source":10,"target":23},{"source":10,"target":22},{"source":10,"target":23},{"source":10,"target":22},{"source":10,"target":23},{"source":22,"target":5},{"source":22,"target":24},{"source":22,"target":25},{"source":22,"target":10},{"source":22,"target":10},{"source":23,"target":4},{"source":23,"target":26},{"source":23,"target":27},{"source":23,"target":10},{"source":23,"target":10},{"source":11,"target":28},{"source":11,"target":29},{"source":11,"target":28},{"source":11,"target":29},{"source":11,"target":28},{"source":11,"target":29},{"source":28,"target":4},{"source":28,"target":30},{"source":28,"target":31},{"source":28,"target":11},{"source":28,"target":11},{"source":29,"target":3},{"source":29,"target":32},{"source":29,"target":33},{"source":29,"target":11},{"source":29,"target":11},{"source":12,"target":34},{"source":12,"target":35},{"source":12,"target":34},{"source":12,"target":35},{"source":12,"target":34},{"source":34,"target":6},{"source":34,"target":36},{"source":34,"target":37},{"source":34,"target":12},{"source":34,"target":12},{"source":35,"target":5},{"source":35,"target":38},{"source":35,"target":39},{"source":35,"target":12},{"source":35,"target":12}],"multigraph":true}