{"directed":true,"nodes":[{"viewpoint":null,"visibility":"PUBLIC_LITERAL","qualifiedName":"model","name":"model","id":0,"URI":null,"eClass":"Model"},{"visibility":"PUBLIC_LITERAL","id":1,"eClass":"PackageImport"},{"isSingleExecution":false,"isReadOnly":false,"visibility":"PUBLIC_LITERAL","qualifiedName":"model::Activity","name":"Activity","id":2,"isActive":false,"isReentrant":true,"isLeaf":false,"isAbstract":false,"isFinalSpecialization":false,"eClass":"Activity"},{"visibility":"PUBLIC_LITERAL","qualifiedName":"ControlFlow","name":"ControlFlow","id":3,"isLeaf":false,"eClass":"ControlFlow"},{"visibility":"PUBLIC_LITERAL","qualifiedName":"ControlFlow","name":"ControlFlow","id":4,"isLeaf":false,"eClass":"ControlFlow"},{"visibility":"PUBLIC_LITERAL","qualifiedName":"Create coffe","isLocallyReentrant":false,"name":"Create coffe","language":[],"id":5,"body":[],"isLeaf":false,"eClass":"OpaqueAction"},{"visibility":"PUBLIC_LITERAL","qualifiedName":"Start Button","name":"Start Button","id":6,"isLeaf":false,"eClass":"InitialNode"},{"visibility":"PUBLIC_LITERAL","qualifiedName":"MergeNode","name":"MergeNode","id":7,"isLeaf":false,"eClass":"MergeNode"},{"visibility":"PUBLIC_LITERAL","qualifiedName":"OpaqueAction","isLocallyReentrant":false,"name":"OpaqueAction","language":[],"id":8,"body":[],"isLeaf":false,"eClass":"OpaqueAction"},{"visibility":"PUBLIC_LITERAL","qualifiedName":"FlowFinalNode","name":"FlowFinalNode","id":9,"isLeaf":false,"eClass":"FlowFinae2","id":16,"isLeaf":false,"eClass":"FlowFinalNode"},{"visibility":"PUBLIC_LITERAL","qualifiedName":"MergeNode2","name":"MergeNode2","id":17,"isLeaf":false,"eClass":"MergeNode"},{"visibility":"PUBLIC_LITERAL","qualifiedName":"ForkNode2","name":"ForkNode2","id":18,"isLeaf":false,"eClass":"ForkNode"},{"visibility":"PUBLIC_LITERAL","qualifiedName":"FlowFinalNode3","name":"FlowFinalNode3","id":19,"isLeaf":false,"eClass":"FlowFinalNode"},{"visibility":"PUBLIC_LITERAL","qualifiedName":"InitialNode","name":"InitialNode","id":20,"isLeaf":false,"eClass":"InitialNode"},{"visibility":"PUBLIC_LITERAL","qualifiedName":"OpaqueAction4","isLocallyReentrant":false,"name":"OpaqueAction4","language":[],"id":21,"body":[],"isLeaf":false,"eClass":"OpaqueAction"},{"visibility":"PUBLIC_LITERAL","qualifiedName":"OpaqueAction5","isLocallyReentrant":false,"name":"OpaqueAction5","language":[],"id":22,"body":[],"isLeaf":false,"eClass":"OpaqueAction"},{"visibility":"PUBLIC_LITERAL","qualifiedName":"InitialNode2","name":"InitialNode2","id":23,"isLeaf":false,"eClass":"InitialNode"},{"visibility":"PUBLIC_LITERAL","qualifiedName":"OpaqueAction6","isLocallyReentrant":false,"name":"OpaqueAction6","language":[],"id":24,"body":[],"isLeaf":false,"eClass":"OpaqueAction"},{"visibility":"PUBLIC_LITERAL","qualifiedName":"MergeNode3","name":"MergeNode3","id":25,"isLeaf":false,"eClass":"MergeNode"},{"visibility":"PUBLIC_LITERAL","qualifiedName":null,"name":null,"id":26,"value":"true","eClass":"LiteralString"},{"visibility":"PUBLIC_LITERAL","qualifiedName":null,"name":null,"id":27,"value":"true","eClass":"LiteralString"}],"links":[{"source":0,"target":1},{"source":0,"target":2},{"source":1,"target":0},{"source":2,"target":3},{"source":2,"target":4},{"source":2,"target":5},{"source":2,"target":6},{"source":2,"target":7},{"source":2,"target":8},{"source":2,"target":9},{"source":2,"target":10},{"source":2,"target":11},{"source":2,"target":12},{"source":2,"target":13},{"source":2,"target":14},{"source":2,"target":15},{"source":2,"target":16},{"source":2,"target":17},{"source":2,"target":18},{"source":2,"target":19},{"source":2,"target":20},{"source":2,"target":21},{"source":2,"target":22},{"source":2,"target":23},{"source":2,"target":24},{"source":2,"target":25},{"source":3,"target":2},{"source":3,"target":26},{"source":3,"target":7},{"source":3,"target":6},{"source":4,"target":2},{"source":4,"target":27},{"source":4,"target":5},{"source":4,"target":7},{"source":5,"target":4},{"source":6,"target":3},{"source":7,"target":3},{"source":7,"target":4}],"multigraph":true}